odata/__init__.py
odata/client.py
odata_bc-0.1.4.post1.dist-info/METADATA
odata_bc-0.1.4.post1.dist-info/WHEEL
odata_bc-0.1.4.post1.dist-info/licenses/LICENSE
odata_bc-0.1.4.post1.dist-info/RECORD
