Metadata-Version: 2.4
Name: odata-bc
Version: 0.1.4.post1
Summary: Simple OData client with query builder
License-File: LICENSE
Requires-Python: >=3.13
Requires-Dist: loguru>=0.7.3
Requires-Dist: pandas>=2.2.3
Requires-Dist: requests>=2.32.3
Provides-Extra: test
Requires-Dist: pytest>=8.3.4; extra == 'test'
